tetuntokenizer/__init__.py
tetuntokenizer/tetun_patterns.py
tetuntokenizer/tokenizer.py
tetun_tokenizer-1.2.3.dist-info/METADATA
tetun_tokenizer-1.2.3.dist-info/WHEEL
tetun_tokenizer-1.2.3.dist-info/licenses/LICENSE
tetun_tokenizer-1.2.3.dist-info/RECORD
